dnz_client/__init__.py
dnz_client/client.py
dnzapi-0.0.1.dist-info/COPYING
dnzapi-0.0.1.dist-info/COPYING.LESSER
dnzapi-0.0.1.dist-info/METADATA
dnzapi-0.0.1.dist-info/WHEEL
dnzapi-0.0.1.dist-info/top_level.txt
dnzapi-0.0.1.dist-info/RECORD
