Metadata-Version: 2.1
Name: dnzapi
Version: 0.0.1
Summary: Client for querying DigitalNZ via its API
Author-email: Jamie Norrish <jamie@artefact.org.nz>
License: GNU LESSER GENERAL PUBLIC LICENSE
Project-URL: Homepage, https://github.com/ucdh/digitalnz-api-python
Project-URL: Bug Tracker, https://github.com/ucdh/digitalnz-api-python/issues
Classifier: Development Status :: 4 - Beta
Classifier: Intended Audience :: Developers
Classifier: License :: OSI Approved :: GNU Lesser General Public License v3 or later (LGPLv3+)
Classifier: Operating System :: OS Independent
Classifier: Programming Language :: Python :: 3
License-File: COPYING
License-File: COPYING.LESSER
Requires-Dist: api-client
